zmathlib/__init__.py
zmathlib/zmathlib.py
zmathlib-0.1.0.dist-info/LICENSE
zmathlib-0.1.0.dist-info/METADATA
zmathlib-0.1.0.dist-info/WHEEL
zmathlib-0.1.0.dist-info/top_level.txt
zmathlib-0.1.0.dist-info/RECORD
