Metadata-Version: 2.1
Name: zmathlib
Version: 0.1.0
Summary: This package helps to do maths by Zan X Technologies
Author-email: Zandora Space <professor@zandora.space>
License: MIT License        
Project-URL: Homepage, https://github.com/zandora-space/zmathlib
Project-URL: Bug Tracker, https://github.com/zandora-space/zmathlib/issues
Classifier: Programming Language :: Python :: 3
Classifier: License :: OSI Approved :: MIT License
Classifier: Operating System :: OS Independent
Requires-Python: >=3.7
License-File: LICENSE
